{
  "generated_at": "2026-04-09T08:59:36",
  "horizon": "long",
  "horizon_label": "Long terme",
  "stocks": [
    {
      "symbol": "ADH",
      "display_name": "DOUJA PROM ADDOHA",
      "sector": "Immobilier",
      "per_family": {
        "sma": {
          "score_pct": 17.57,
          "label": "Haussier"
        },
        "macd": {
          "score_pct": 100.0,
          "label": "Très haussier"
        },
        "rsi": {
          "score_pct": -100.0,
          "label": "Très suracheté"
        },
        "obv": {
          "score_pct": 100.0,
          "label": "Forte accumulation"
        }
      },
      "categories": {
        "tendance": {
          "score_pct": 58.78,
          "label": "Très haussier",
          "families": [
            "sma",
            "macd"
          ]
        },
        "oscillation": {
          "score_pct": -100.0,
          "label": "Très suracheté",
          "families": [
            "rsi"
          ]
        },
        "volume": {
          "score_pct": 100.0,
          "label": "Forte accumulation",
          "families": [
            "obv"
          ]
        }
      },
      "aggregate_score_pct": 29.39,
      "aggregate_signal_label": "Achat"
    },
    {
      "symbol": "ADI",
      "display_name": "ALLIANCES",
      "sector": "Immobilier",
      "per_family": {
        "sma": {
          "score_pct": 0.0,
          "label": "Neutre"
        },
        "macd": {
          "score_pct": 0.0,
          "label": "Neutre"
        },
        "rsi": {
          "score_pct": 0.0,
          "label": "Neutre"
        },
        "obv": {
          "score_pct": 0.0,
          "label": "Neutre"
        }
      },
      "categories": {
        "tendance": {
          "score_pct": 0.0,
          "label": "Neutre",
          "families": [
            "sma",
            "macd"
          ]
        },
        "oscillation": {
          "score_pct": 0.0,
          "label": "Normal",
          "families": [
            "rsi"
          ]
        },
        "volume": {
          "score_pct": 0.0,
          "label": "Neutre",
          "families": [
            "obv"
          ]
        }
      },
      "aggregate_score_pct": 0.0,
      "aggregate_signal_label": "Neutre"
    },
    {
      "symbol": "AKT",
      "display_name": "AKDITAL",
      "sector": "Santé",
      "per_family": {
        "sma": {
          "score_pct": 0.0,
          "label": "Neutre"
        },
        "macd": {
          "score_pct": 0.0,
          "label": "Neutre"
        },
        "rsi": {
          "score_pct": 0.0,
          "label": "Neutre"
        },
        "obv": {
          "score_pct": 0.0,
          "label": "Neutre"
        }
      },
      "categories": {
        "tendance": {
          "score_pct": 0.0,
          "label": "Neutre",
          "families": [
            "sma",
            "macd"
          ]
        },
        "oscillation": {
          "score_pct": 0.0,
          "label": "Normal",
          "families": [
            "rsi"
          ]
        },
        "volume": {
          "score_pct": 0.0,
          "label": "Neutre",
          "families": [
            "obv"
          ]
        }
      },
      "aggregate_score_pct": 0.0,
      "aggregate_signal_label": "Neutre"
    },
    {
      "symbol": "ATW",
      "display_name": "ATTIJARIWAFA BANK",
      "sector": "Banques",
      "per_family": {
        "sma": {
          "score_pct": -100.0,
          "label": "Très baissier"
        },
        "macd": {
          "score_pct": 100.0,
          "label": "Très haussier"
        },
        "rsi": {
          "score_pct": 0.0,
          "label": "Normal"
        },
        "obv": {
          "score_pct": 19.41,
          "label": "Accumulation"
        }
      },
      "categories": {
        "tendance": {
          "score_pct": 0.0,
          "label": "Neutre",
          "families": [
            "sma",
            "macd"
          ]
        },
        "oscillation": {
          "score_pct": 0.0,
          "label": "Normal",
          "families": [
            "rsi"
          ]
        },
        "volume": {
          "score_pct": 19.41,
          "label": "Accumulation",
          "families": [
            "obv"
          ]
        }
      },
      "aggregate_score_pct": 4.85,
      "aggregate_signal_label": "Neutre"
    },
    {
      "symbol": "BCP",
      "display_name": "BCP",
      "sector": "Banques",
      "per_family": {
        "sma": {
          "score_pct": -100.0,
          "label": "Très baissier"
        },
        "macd": {
          "score_pct": 100.0,
          "label": "Très haussier"
        },
        "rsi": {
          "score_pct": 0.0,
          "label": "Normal"
        },
        "obv": {
          "score_pct": 41.48,
          "label": "Accumulation"
        }
      },
      "categories": {
        "tendance": {
          "score_pct": 0.0,
          "label": "Neutre",
          "families": [
            "sma",
            "macd"
          ]
        },
        "oscillation": {
          "score_pct": 0.0,
          "label": "Normal",
          "families": [
            "rsi"
          ]
        },
        "volume": {
          "score_pct": 41.48,
          "label": "Accumulation",
          "families": [
            "obv"
          ]
        }
      },
      "aggregate_score_pct": 10.37,
      "aggregate_signal_label": "Neutre"
    },
    {
      "symbol": "CAP",
      "display_name": "CASH PLUS S.A",
      "sector": "Sociétés de financement",
      "per_family": {
        "sma": {
          "score_pct": 0.0,
          "label": "Neutre"
        },
        "macd": {
          "score_pct": 0.0,
          "label": "Neutre"
        },
        "rsi": {
          "score_pct": 0.0,
          "label": "Normal"
        },
        "obv": {
          "score_pct": 0.0,
          "label": "Neutre"
        }
      },
      "categories": {
        "tendance": {
          "score_pct": 0.0,
          "label": "Neutre",
          "families": [
            "sma",
            "macd"
          ]
        },
        "oscillation": {
          "score_pct": 0.0,
          "label": "Normal",
          "families": [
            "rsi"
          ]
        },
        "volume": {
          "score_pct": 0.0,
          "label": "Neutre",
          "families": [
            "obv"
          ]
        }
      },
      "aggregate_score_pct": 0.0,
      "aggregate_signal_label": "Neutre"
    },
    {
      "symbol": "CDM",
      "display_name": "CDM",
      "sector": "Banques",
      "per_family": {
        "sma": {
          "score_pct": 0.0,
          "label": "Neutre"
        },
        "macd": {
          "score_pct": 100.0,
          "label": "Très haussier"
        },
        "rsi": {
          "score_pct": 0.0,
          "label": "Neutre"
        },
        "obv": {
          "score_pct": 100.0,
          "label": "Forte accumulation"
        }
      },
      "categories": {
        "tendance": {
          "score_pct": 50.0,
          "label": "Haussier",
          "families": [
            "sma",
            "macd"
          ]
        },
        "oscillation": {
          "score_pct": 0.0,
          "label": "Normal",
          "families": [
            "rsi"
          ]
        },
        "volume": {
          "score_pct": 100.0,
          "label": "Forte accumulation",
          "families": [
            "obv"
          ]
        }
      },
      "aggregate_score_pct": 50.0,
      "aggregate_signal_label": "Achat"
    },
    {
      "symbol": "CFG",
      "display_name": "CFG BANK",
      "sector": "Banques",
      "per_family": {
        "sma": {
          "score_pct": 0.0,
          "label": "Neutre"
        },
        "macd": {
          "score_pct": 0.0,
          "label": "Neutre"
        },
        "rsi": {
          "score_pct": 0.0,
          "label": "Neutre"
        },
        "obv": {
          "score_pct": 0.0,
          "label": "Neutre"
        }
      },
      "categories": {
        "tendance": {
          "score_pct": 0.0,
          "label": "Neutre",
          "families": [
            "sma",
            "macd"
          ]
        },
        "oscillation": {
          "score_pct": 0.0,
          "label": "Normal",
          "families": [
            "rsi"
          ]
        },
        "volume": {
          "score_pct": 0.0,
          "label": "Neutre",
          "families": [
            "obv"
          ]
        }
      },
      "aggregate_score_pct": 0.0,
      "aggregate_signal_label": "Neutre"
    },
    {
      "symbol": "CSR",
      "display_name": "COSUMAR",
      "sector": "Agroalimentaire",
      "per_family": {
        "sma": {
          "score_pct": 0.0,
          "label": "Neutre"
        },
        "macd": {
          "score_pct": 100.0,
          "label": "Très haussier"
        },
        "rsi": {
          "score_pct": 0.0,
          "label": "Normal"
        },
        "obv": {
          "score_pct": -34.61,
          "label": "Distribution"
        }
      },
      "categories": {
        "tendance": {
          "score_pct": 50.0,
          "label": "Haussier",
          "families": [
            "sma",
            "macd"
          ]
        },
        "oscillation": {
          "score_pct": 0.0,
          "label": "Normal",
          "families": [
            "rsi"
          ]
        },
        "volume": {
          "score_pct": -34.61,
          "label": "Distribution",
          "families": [
            "obv"
          ]
        }
      },
      "aggregate_score_pct": 16.35,
      "aggregate_signal_label": "Achat"
    },
    {
      "symbol": "GTM",
      "display_name": "SGTM",
      "sector": "BTP",
      "per_family": {
        "sma": {
          "score_pct": 0.0,
          "label": "Neutre"
        },
        "macd": {
          "score_pct": 0.0,
          "label": "Neutre"
        },
        "rsi": {
          "score_pct": 0.0,
          "label": "Neutre"
        },
        "obv": {
          "score_pct": 0.0,
          "label": "Neutre"
        }
      },
      "categories": {
        "tendance": {
          "score_pct": 0.0,
          "label": "Neutre",
          "families": [
            "sma",
            "macd"
          ]
        },
        "oscillation": {
          "score_pct": 0.0,
          "label": "Normal",
          "families": [
            "rsi"
          ]
        },
        "volume": {
          "score_pct": 0.0,
          "label": "Neutre",
          "families": [
            "obv"
          ]
        }
      },
      "aggregate_score_pct": 0.0,
      "aggregate_signal_label": "Neutre"
    },
    {
      "symbol": "IAM",
      "display_name": "ITISSALAT AL-MAGHRIB",
      "sector": "Télécommunications",
      "per_family": {
        "sma": {
          "score_pct": 9.09,
          "label": "Neutre"
        },
        "macd": {
          "score_pct": 100.0,
          "label": "Très haussier"
        },
        "rsi": {
          "score_pct": 0.0,
          "label": "Normal"
        },
        "obv": {
          "score_pct": 100.0,
          "label": "Forte accumulation"
        }
      },
      "categories": {
        "tendance": {
          "score_pct": 54.55,
          "label": "Très haussier",
          "families": [
            "sma",
            "macd"
          ]
        },
        "oscillation": {
          "score_pct": 0.0,
          "label": "Normal",
          "families": [
            "rsi"
          ]
        },
        "volume": {
          "score_pct": 100.0,
          "label": "Forte accumulation",
          "families": [
            "obv"
          ]
        }
      },
      "aggregate_score_pct": 52.27,
      "aggregate_signal_label": "Achat fort"
    },
    {
      "symbol": "JET",
      "display_name": "JET CONTRACTORS",
      "sector": "BTP",
      "per_family": {
        "sma": {
          "score_pct": 0.0,
          "label": "Neutre"
        },
        "macd": {
          "score_pct": 0.0,
          "label": "Neutre"
        },
        "rsi": {
          "score_pct": 0.0,
          "label": "Neutre"
        },
        "obv": {
          "score_pct": 0.0,
          "label": "Neutre"
        }
      },
      "categories": {
        "tendance": {
          "score_pct": 0.0,
          "label": "Neutre",
          "families": [
            "sma",
            "macd"
          ]
        },
        "oscillation": {
          "score_pct": 0.0,
          "label": "Normal",
          "families": [
            "rsi"
          ]
        },
        "volume": {
          "score_pct": 0.0,
          "label": "Neutre",
          "families": [
            "obv"
          ]
        }
      },
      "aggregate_score_pct": 0.0,
      "aggregate_signal_label": "Neutre"
    },
    {
      "symbol": "LHM",
      "display_name": "LAFARGEHOLCIM MAROC",
      "sector": "BTP",
      "per_family": {
        "sma": {
          "score_pct": 0.0,
          "label": "Neutre"
        },
        "macd": {
          "score_pct": 0.0,
          "label": "Neutre"
        },
        "rsi": {
          "score_pct": 0.0,
          "label": "Neutre"
        },
        "obv": {
          "score_pct": 0.0,
          "label": "Neutre"
        }
      },
      "categories": {
        "tendance": {
          "score_pct": 0.0,
          "label": "Neutre",
          "families": [
            "sma",
            "macd"
          ]
        },
        "oscillation": {
          "score_pct": 0.0,
          "label": "Normal",
          "families": [
            "rsi"
          ]
        },
        "volume": {
          "score_pct": 0.0,
          "label": "Neutre",
          "families": [
            "obv"
          ]
        }
      },
      "aggregate_score_pct": 0.0,
      "aggregate_signal_label": "Neutre"
    },
    {
      "symbol": "MSA",
      "display_name": "SODEP-Marsa Maroc",
      "sector": "Transport",
      "per_family": {
        "sma": {
          "score_pct": -64.81,
          "label": "Très baissier"
        },
        "macd": {
          "score_pct": 100.0,
          "label": "Très haussier"
        },
        "rsi": {
          "score_pct": 0.0,
          "label": "Normal"
        },
        "obv": {
          "score_pct": 49.6,
          "label": "Accumulation"
        }
      },
      "categories": {
        "tendance": {
          "score_pct": 17.59,
          "label": "Haussier",
          "families": [
            "sma",
            "macd"
          ]
        },
        "oscillation": {
          "score_pct": 0.0,
          "label": "Normal",
          "families": [
            "rsi"
          ]
        },
        "volume": {
          "score_pct": 49.6,
          "label": "Accumulation",
          "families": [
            "obv"
          ]
        }
      },
      "aggregate_score_pct": 21.2,
      "aggregate_signal_label": "Achat"
    },
    {
      "symbol": "SNA",
      "display_name": "Stokvis Nord Afrique (Ste) SA",
      "sector": "Distribution",
      "per_family": {
        "sma": {
          "score_pct": 0.0,
          "label": "Neutre"
        },
        "macd": {
          "score_pct": 0.0,
          "label": "Neutre"
        },
        "rsi": {
          "score_pct": 0.0,
          "label": "Neutre"
        },
        "obv": {
          "score_pct": 0.0,
          "label": "Neutre"
        }
      },
      "categories": {
        "tendance": {
          "score_pct": 0.0,
          "label": "Neutre",
          "families": [
            "sma",
            "macd"
          ]
        },
        "oscillation": {
          "score_pct": 0.0,
          "label": "Normal",
          "families": [
            "rsi"
          ]
        },
        "volume": {
          "score_pct": 0.0,
          "label": "Neutre",
          "families": [
            "obv"
          ]
        }
      },
      "aggregate_score_pct": 0.0,
      "aggregate_signal_label": "Neutre"
    },
    {
      "symbol": "TGC",
      "display_name": "TGCC S.A",
      "sector": "BTP",
      "per_family": {
        "sma": {
          "score_pct": 100.0,
          "label": "Très haussier"
        },
        "macd": {
          "score_pct": -4.11,
          "label": "Neutre"
        },
        "rsi": {
          "score_pct": 0.0,
          "label": "Normal"
        },
        "obv": {
          "score_pct": -35.91,
          "label": "Distribution"
        }
      },
      "categories": {
        "tendance": {
          "score_pct": 47.95,
          "label": "Haussier",
          "families": [
            "sma",
            "macd"
          ]
        },
        "oscillation": {
          "score_pct": 0.0,
          "label": "Normal",
          "families": [
            "rsi"
          ]
        },
        "volume": {
          "score_pct": -35.91,
          "label": "Distribution",
          "families": [
            "obv"
          ]
        }
      },
      "aggregate_score_pct": 15.0,
      "aggregate_signal_label": "Neutre"
    },
    {
      "symbol": "VCN",
      "display_name": "Vicenne",
      "sector": "Santé",
      "per_family": {
        "sma": {
          "score_pct": 0.0,
          "label": "Neutre"
        },
        "macd": {
          "score_pct": 0.0,
          "label": "Neutre"
        },
        "rsi": {
          "score_pct": 0.0,
          "label": "Neutre"
        },
        "obv": {
          "score_pct": 0.0,
          "label": "Neutre"
        }
      },
      "categories": {
        "tendance": {
          "score_pct": 0.0,
          "label": "Neutre",
          "families": [
            "sma",
            "macd"
          ]
        },
        "oscillation": {
          "score_pct": 0.0,
          "label": "Normal",
          "families": [
            "rsi"
          ]
        },
        "volume": {
          "score_pct": 0.0,
          "label": "Neutre",
          "families": [
            "obv"
          ]
        }
      },
      "aggregate_score_pct": 0.0,
      "aggregate_signal_label": "Neutre"
    }
  ],
  "sectors": [
    {
      "sector": "Agroalimentaire",
      "stock_count": 1,
      "aggregate_score_pct": 16.35,
      "aggregate_signal_label": "Achat",
      "per_family": {
        "sma": {
          "score_pct": 0.0,
          "label": "Neutre"
        },
        "macd": {
          "score_pct": 100.0,
          "label": "Très haussier"
        },
        "rsi": {
          "score_pct": 0.0,
          "label": "Normal"
        },
        "obv": {
          "score_pct": -34.61,
          "label": "Distribution"
        }
      }
    },
    {
      "sector": "BTP",
      "stock_count": 4,
      "aggregate_score_pct": 3.75,
      "aggregate_signal_label": "Neutre",
      "per_family": {
        "sma": {
          "score_pct": 25.0,
          "label": "Haussier"
        },
        "macd": {
          "score_pct": -1.03,
          "label": "Neutre"
        },
        "rsi": {
          "score_pct": 0.0,
          "label": "Normal"
        },
        "obv": {
          "score_pct": -8.98,
          "label": "Neutre"
        }
      }
    },
    {
      "sector": "Banques",
      "stock_count": 4,
      "aggregate_score_pct": 16.3,
      "aggregate_signal_label": "Achat",
      "per_family": {
        "sma": {
          "score_pct": -50.0,
          "label": "Baissier"
        },
        "macd": {
          "score_pct": 75.0,
          "label": "Très haussier"
        },
        "rsi": {
          "score_pct": 0.0,
          "label": "Normal"
        },
        "obv": {
          "score_pct": 40.22,
          "label": "Accumulation"
        }
      }
    },
    {
      "sector": "Distribution",
      "stock_count": 1,
      "aggregate_score_pct": 0.0,
      "aggregate_signal_label": "Neutre",
      "per_family": {
        "sma": {
          "score_pct": 0.0,
          "label": "Neutre"
        },
        "macd": {
          "score_pct": 0.0,
          "label": "Neutre"
        },
        "rsi": {
          "score_pct": 0.0,
          "label": "Normal"
        },
        "obv": {
          "score_pct": 0.0,
          "label": "Neutre"
        }
      }
    },
    {
      "sector": "Immobilier",
      "stock_count": 2,
      "aggregate_score_pct": 14.7,
      "aggregate_signal_label": "Neutre",
      "per_family": {
        "sma": {
          "score_pct": 8.79,
          "label": "Neutre"
        },
        "macd": {
          "score_pct": 50.0,
          "label": "Haussier"
        },
        "rsi": {
          "score_pct": -50.0,
          "label": "Suracheté"
        },
        "obv": {
          "score_pct": 50.0,
          "label": "Accumulation"
        }
      }
    },
    {
      "sector": "Santé",
      "stock_count": 2,
      "aggregate_score_pct": 0.0,
      "aggregate_signal_label": "Neutre",
      "per_family": {
        "sma": {
          "score_pct": 0.0,
          "label": "Neutre"
        },
        "macd": {
          "score_pct": 0.0,
          "label": "Neutre"
        },
        "rsi": {
          "score_pct": 0.0,
          "label": "Normal"
        },
        "obv": {
          "score_pct": 0.0,
          "label": "Neutre"
        }
      }
    },
    {
      "sector": "Sociétés de financement",
      "stock_count": 1,
      "aggregate_score_pct": 0.0,
      "aggregate_signal_label": "Neutre",
      "per_family": {
        "sma": {
          "score_pct": 0.0,
          "label": "Neutre"
        },
        "macd": {
          "score_pct": 0.0,
          "label": "Neutre"
        },
        "rsi": {
          "score_pct": 0.0,
          "label": "Normal"
        },
        "obv": {
          "score_pct": 0.0,
          "label": "Neutre"
        }
      }
    },
    {
      "sector": "Transport",
      "stock_count": 1,
      "aggregate_score_pct": 21.2,
      "aggregate_signal_label": "Achat",
      "per_family": {
        "sma": {
          "score_pct": -64.81,
          "label": "Très baissier"
        },
        "macd": {
          "score_pct": 100.0,
          "label": "Très haussier"
        },
        "rsi": {
          "score_pct": 0.0,
          "label": "Normal"
        },
        "obv": {
          "score_pct": 49.6,
          "label": "Accumulation"
        }
      }
    },
    {
      "sector": "Télécommunications",
      "stock_count": 1,
      "aggregate_score_pct": 52.27,
      "aggregate_signal_label": "Achat fort",
      "per_family": {
        "sma": {
          "score_pct": 9.09,
          "label": "Neutre"
        },
        "macd": {
          "score_pct": 100.0,
          "label": "Très haussier"
        },
        "rsi": {
          "score_pct": 0.0,
          "label": "Normal"
        },
        "obv": {
          "score_pct": 100.0,
          "label": "Forte accumulation"
        }
      }
    }
  ],
  "index": {
    "name": "MASI",
    "stock_count": 17,
    "aggregate_score_pct": 11.73,
    "aggregate_signal_label": "Neutre",
    "per_family": {
      "sma": {
        "score_pct": -8.13,
        "label": "Neutre"
      },
      "macd": {
        "score_pct": 40.93,
        "label": "Haussier"
      },
      "rsi": {
        "score_pct": -5.88,
        "label": "Normal"
      },
      "obv": {
        "score_pct": 20.0,
        "label": "Accumulation"
      }
    },
    "breadth": {
      "achat": 5,
      "neutre": 12,
      "vente": 0,
      "indisponible": 0
    }
  }
}